pytest_capture_deprecatedwarnings/__init__.py
pytest_capture_deprecatedwarnings-0.2.dist-info/METADATA
pytest_capture_deprecatedwarnings-0.2.dist-info/WHEEL
pytest_capture_deprecatedwarnings-0.2.dist-info/entry_points.txt
pytest_capture_deprecatedwarnings-0.2.dist-info/top_level.txt
pytest_capture_deprecatedwarnings-0.2.dist-info/RECORD
