Metadata-Version: 2.1
Name: pytest-capture-deprecatedwarnings
Version: 0.2
Summary: pytest plugin to capture all deprecatedwarnings and put them in one file
Home-page: https://github.com/psycojoker/pytest-capture-deprecatedwarnings
Author: Laurent Peuch
Author-email: cortex@worlddomination.be
License: MIT
Platform: UNKNOWN
Requires-Dist: pytest
